tests/test_cli.py
tests/test_config_loader.py
tests/test_decorators.py
tests/test_integration.py
tests/test_registry.py
tests/test_utils.py
tests/fixtures/configs/base.py
tests/fixtures/configs/model/large.py
tests/fixtures/configs/model/small.py
pydraconf/__init__.py
pydraconf/base_config.py
pydraconf/cli.py
pydraconf/config_loader.py
pydraconf/decorators.py
pydraconf/logger.py
pydraconf/py.typed
pydraconf/registry.py
pydraconf/utils.py
pydraconf-0.1.0.dist-info/METADATA
pydraconf-0.1.0.dist-info/WHEEL
pydraconf-0.1.0.dist-info/licenses/LICENSE
pydraconf-0.1.0.dist-info/RECORD
