Metadata-Version: 2.4
Name: pydraconf
Version: 0.1.0
Summary: Python-native hierarchical configuration management with Pydantic. Like Hydra, but for YAML-haters.
Author-email: Andrey Goncharov <andrey@faillearnrepeat.net>
License-File: LICENSE
Requires-Python: >=3.10
Requires-Dist: pydantic>=2.0
Requires-Dist: tomli>=1.0.0; python_full_version < '3.11'
